swps_tweet_download_client/__init__.py
swps_tweet_download_client/application/__init__.py
swps_tweet_download_client/application/file_merger.py
swps_tweet_download_client/application/minio_downloader.py
swps_tweet_download_client/application/utils.py
swps_tweet_download_client/config.py
swps_tweet_download_client/domain/__init__.py
swps_tweet_download_client/domain/minio_credentials.py
swps_tweet_download_client/main.py
swps_tweet_download_client-0.2.1.dist-info/entry_points.txt
swps_tweet_download_client-0.2.1.dist-info/WHEEL
swps_tweet_download_client-0.2.1.dist-info/METADATA
swps_tweet_download_client-0.2.1.dist-info/RECORD
