Metadata-Version: 2.1
Name: swps-tweet-download-client
Version: 0.2.1
Summary: 
Author: Marcin Wątroba
Author-email: marcin.watroba@pwr.edu.pl
Requires-Python: >=3.8,<4.0
Classifier: Programming Language :: Python :: 3
Classifier: Programming Language :: Python :: 3.10
Classifier: Programming Language :: Python :: 3.8
Classifier: Programming Language :: Python :: 3.9
Requires-Dist: PyYAML (>=6.0,<7.0)
Requires-Dist: XlsxWriter (>=3.0.2,<4.0.0)
Requires-Dist: arrow (>=1.2.2,<2.0.0)
Requires-Dist: click (>=8.0.3,<9.0.0)
Requires-Dist: dynaconf (>=3.1.7,<4.0.0)
Requires-Dist: minio (>=7.1.2,<8.0.0)
Requires-Dist: pandas (>=1.4.0,<2.0.0)
